[
  {
    "id": 1,
    "ประเภท": "critical",
    "หัวข้อ": "อุปกรณ์ Offline",
    "รายละเอียด": "Firewall กลางจังหวัดพิษณุโลกไม่ตอบสนองตั้งแต่ 10:45 น.",
    "เวลา": "2025-12-01 10:46",
    "อุปกรณ์": "Firewall @ ศาลากลางพิษณุโลก",
    "จังหวัด": "พิษณุโลก"
  },
  {
    "id": 2,
    "ประเภท": "warning",
    "หัวข้อ": "สัญญาณ AP ลดลง",
    "รายละเอียด": "Access Point อาคารอำเภอหล่มสัก ความแรงสัญญาณต่ำกว่าปกติ",
    "เวลา": "2025-12-01 09:20",
    "อุปกรณ์": "Access Point @ อำเภอหล่มสัก",
    "จังหวัด": "เพชรบูรณ์"
  },
  {
    "id": 3,
    "ประเภท": "request",
    "หัวข้อ": "คำร้องขอซ่อมอุปกรณ์ใหม่",
    "รายละเอียด": "จังหวัดตากแจ้งงานซ่อม Switch ชั้น 3 ไม่กระจายสัญญาณ",
    "เวลา": "2025-12-01 08:12",
    "ผู้ร้องขอ": "สำนักงานจังหวัดตาก",
    "สถานะคำร้อง": "รอตรวจสอบ"
  },
  {
    "id": 4,
    "ประเภท": "maintenance",
    "หัวข้อ": "อยู่ระหว่างการซ่อม",
    "รายละเอียด": "CCTV ทางหลวงหมายเลข 12 อยู่ในระหว่างการซ่อมแซม",
    "เวลา": "2025-11-30 16:40",
    "ผู้ดำเนินการ": "ICT8"
  },
  {
    "id": 5,
    "ประเภท": "info",
    "หัวข้อ": "แก้ไขปัญหาเรียบร้อย",
    "รายละเอียด": "Router รพ.พุทธชินราช ออนไลน์อีกครั้งหลังปรับปรุงระบบ",
    "เวลา": "2025-11-30 15:10",
    "อุปกรณ์": "Router @ รพ.พุทธชินราช"
  },
  {
    "id": 6,
    "ประเภท": "critical",
    "หัวข้อ": "Switch ไม่ตอบสนอง",
    "รายละเอียด": "Core Switch ศาลากลางเพชรบูรณ์หยุดทำงานกะทันหัน",
    "เวลา": "2025-12-01 10:05",
    "อุปกรณ์": "Core Switch @ ศาลากลางเพชรบูรณ์",
    "จังหวัด": "เพชรบูรณ์"
  },
  {
    "id": 7,
    "ประเภท": "warning",
    "หัวข้อ": "Ping หน่วงสูง",
    "รายละเอียด": "Router พิจิตรมีค่า latency เกิน 250 ms",
    "เวลา": "2025-12-01 09:50",
    "อุปกรณ์": "Router @ สำนักงานจังหวัดพิจิตร",
    "จังหวัด": "พิจิตร"
  },
  {
    "id": 8,
    "ประเภท": "info",
    "หัวข้อ": "อุปกรณ์กลับมาออนไลน์",
    "รายละเอียด": "Access Point อาคารอำเภอพรหมพิรามกลับมาออนไลน์",
    "เวลา": "2025-12-01 09:40",
    "อุปกรณ์": "Access Point @ อำเภอพรหมพิราม",
    "จังหวัด": "พิษณุโลก"
  },
  {
    "id": 9,
    "ประเภท": "request",
    "หัวข้อ": "แจ้งเปลี่ยนแบตเตอรี่ UPS",
    "รายละเอียด": "UPS ที่ว่าการอำเภอแม่ระมาดต้องการเปลี่ยนแบตเตอรี่",
    "เวลา": "2025-12-01 09:10",
    "ผู้ร้องขอ": "ที่ว่าการอำเภอแม่ระมาด",
    "สถานะคำร้อง": "รอตรวจสอบ"
  },
  {
    "id": 10,
    "ประเภท": "maintenance",
    "หัวข้อ": "อัปเดตเฟิร์มแวร์ Firewall",
    "รายละเอียด": "กำลังอัปเกรดเวอร์ชัน Firewall อำเภอเมืองอุตรดิตถ์",
    "เวลา": "2025-12-01 08:30",
    "ผู้ดำเนินการ": "ICT8"
  },
  {
    "id": 11,
    "ประเภท": "critical",
    "หัวข้อ": "CCTV ล้มเหลว",
    "รายละเอียด": "CCTV จุดตรวจแม่สอดขัดข้องไม่ส่งภาพ",
    "เวลา": "2025-11-30 23:55",
    "อุปกรณ์": "CCTV @ จุดตรวจแม่สอด",
    "จังหวัด": "ตาก"
  },
  {
    "id": 12,
    "ประเภท": "warning",
    "หัวข้อ": "สัญญาณ Wi-Fi อ่อน",
    "รายละเอียด": "Access Point ชั้น 2 รพ.อุตรดิตถ์มีสัญญาณต่ำกว่ามาตรฐาน",
    "เวลา": "2025-11-30 20:42",
    "อุปกรณ์": "AP @ รพ.อุตรดิตถ์",
    "จังหวัด": "อุตรดิตถ์"
  },
  {
    "id": 13,
    "ประเภท": "request",
    "หัวข้อ": "คำร้องซ่อมระบบอินเทอร์เน็ต",
    "รายละเอียด": "ศูนย์ราชการพิจิตรแจ้งเน็ตไม่เสถียร",
    "เวลา": "2025-11-30 18:20",
    "ผู้ร้องขอ": "สำนักงานจังหวัดพิจิตร",
    "สถานะคำร้อง": "รอการมอบหมาย"
  },
  {
    "id": 14,
    "ประเภท": "maintenance",
    "หัวข้อ": "ตรวจสอบอัตราการใช้ CPU",
    "รายละเอียด": "Server กลางพิษณุโลกถูกตรวจสอบการใช้งานสูง",
    "เวลา": "2025-11-30 17:10",
    "ผู้ดำเนินการ": "ICT8"
  },
  {
    "id": 15,
    "ประเภท": "info",
    "หัวข้อ": "แก้ไขระบบเน็ตเวิร์กสำเร็จ",
    "รายละเอียด": "Switch พื้นที่อำเภอหนองตมกลับมาทำงานปกติ",
    "เวลา": "2025-11-30 16:12",
    "อุปกรณ์": "Switch @ อำเภอหนองตม",
    "จังหวัด": "พิษณุโลก"
  },
  {
    "id": 16,
    "ประเภท": "critical",
    "หัวข้อ": "Server Down",
    "รายละเอียด": "Server ระบบงานจังหวัดสุโขทัยหยุดทำงาน",
    "เวลา": "2025-11-30 14:55",
    "อุปกรณ์": "Server @ จังหวัดสุโขทัย",
    "จังหวัด": "สุโขทัย"
  },
  {
    "id": 17,
    "ประเภท": "warning",
    "หัวข้อ": "เครือข่ายโหลดสูง",
    "รายละเอียด": "มีการใช้งานสูงผิดปกติบน Router ตำบลบ้านใหม่",
    "เวลา": "2025-11-30 14:30",
    "อุปกรณ์": "Router @ ตำบลบ้านใหม่",
    "จังหวัด": "พิจิตร"
  },
  {
    "id": 18,
    "ประเภท": "info",
    "หัวข้อ": "งานบำรุงรักษาเสร็จสิ้น",
    "รายละเอียด": "Firewall อำเภอชาติตระการพร้อมใช้งาน",
    "เวลา": "2025-11-30 12:22",
    "อุปกรณ์": "Firewall @ อำเภอชาติตระการ",
    "จังหวัด": "พิษณุโลก"
  },
  {
    "id": 19,
    "ประเภท": "request",
    "หัวข้อ": "แจ้งปัญหา Wi-Fi",
    "รายละเอียด": "อำเภอลองแจ้งว่า Wi-Fi หายเป็นช่วง ๆ",
    "เวลา": "2025-11-30 11:40",
    "ผู้ร้องขอ": "ที่ว่าการอำเภอลอง",
    "สถานะคำร้อง": "รอตรวจสอบ"
  },
  {
    "id": 20,
    "ประเภท": "maintenance",
    "หัวข้อ": "เดินสายใหม่",
    "รายละเอียด": "กำลังดำเนินการเปลี่ยนสาย UTP ชั้น 4 สำนักงานสุโขทัย",
    "เวลา": "2025-11-30 10:55",
    "ผู้ดำเนินการ": "ICT8"
  },
  {
    "id": 21,
    "ประเภท": "critical",
    "หัวข้อ": "AP ล่มหลายจุด",
    "รายละเอียด": "Access Point โรงเรียนอนุบาลพิจิตรขัดข้องพร้อมกัน 3 จุด",
    "เวลา": "2025-11-30 09:28",
    "อุปกรณ์": "AP @ โรงเรียนอนุบาลพิจิตร",
    "จังหวัด": "พิจิตร"
  },
  {
    "id": 22,
    "ประเภท": "warning",
    "หัวข้อ": "โหลด Firewall สูง",
    "รายละเอียด": "พบการใช้งาน CPU สูงกว่า 90% ในช่วงเวลาสั้น",
    "เวลา": "2025-11-30 08:55",
    "อุปกรณ์": "Firewall @ อำเภอศรีสำโรง",
    "จังหวัด": "สุโขทัย"
  },
  {
    "id": 23,
    "ประเภท": "info",
    "หัวข้อ": "อุปกรณ์ตรวจสอบผ่านตามรอบ",
    "รายละเอียด": "กล้อง CCTV บนถนนหมายเลข 117 ทำงานปกติ",
    "เวลา": "2025-11-30 08:30",
    "อุปกรณ์": "CCTV @ ถ.117",
    "จังหวัด": "พิษณุโลก"
  },
  {
    "id": 24,
    "ประเภท": "request",
    "หัวข้อ": "แจ้งปัญหา Router",
    "รายละเอียด": "Router ห้องประชุมอุตรดิตถ์รีบูตเองบ่อยครั้ง",
    "เวลา": "2025-11-30 07:45",
    "ผู้ร้องขอ": "อุตรดิตถ์",
    "สถานะคำร้อง": "รอการมอบหมาย"
  },
  {
    "id": 25,
    "ประเภท": "maintenance",
    "หัวข้อ": "ทำความสะอาดตู้ Rack",
    "รายละเอียด": "กำลังปรับปรุงตู้ Rack อำเภอคลองลาน",
    "เวลา": "2025-11-30 06:50",
    "ผู้ดำเนินการ": "ICT8"
  }
]
